[
  {
    "date": 1660228615300,
    "owner_one": {
      "owner_name": "A Team of White Sox",
      "players_received": [
        {
          "Dylan Cease": 17
        }
      ]
    },
    "owner_two": {
      "owner_name": "I Did  Half a Xan",
      "players_received": [
        {
          "Dane Dunning": 7
        }
      ]
    }
  },
  {
    "date": 1660058846283,
    "owner_one": {
      "owner_name": "Trea's Gaze",
      "players_received": [
        {
          "David Robertson": 15
        }
      ]
    },
    "owner_two": {
      "owner_name": "LeMahoe Round 2",
      "players_received": [
        {
          "Jhoan Duran": 15
        },
        {
          "Jose Miranda": 1
        }
      ]
    }
  },
  {
    "date": 1660051920093,
    "owner_one": {
      "owner_name": "Trea's Gaze",
      "players_received": [
        {
          "Kris Bubic": 16
        },
        {
          "Javier Baez": 9
        }
      ]
    },
    "owner_two": {
      "owner_name": "The Cavemen",
      "players_received": [
        {
          "Braxton Garrett": 15
        }
      ]
    }
  },
  {
    "date": 1660050236806,
    "owner_one": {
      "owner_name": "Trea's Gaze",
      "players_received": [
        {
          "David Bednar": 0
        },
        {
          "Fernando Tatis Jr.": 0
        }
      ]
    },
    "owner_two": {
      "owner_name": "I Did  Half a Xan",
      "players_received": [
        {
          "Julio Urias": 44
        }
      ]
    }
  },
  {
    "date": 1660049532414,
    "owner_one": {
      "owner_name": "I Did  Half a Xan",
      "players_received": [
        {
          "Fernando Tatis Jr.": 0
        }
      ]
    },
    "owner_two": {
      "owner_name": "The Cavemen",
      "players_received": [
        {
          "Chris Bassitt": 17
        }
      ]
    }
  },
  {
    "date": 1659986545202,
    "owner_one": {
      "owner_name": "All about The Mets",
      "players_received": [
        {
          "Seiya Suzuki": 17
        }
      ]
    },
    "owner_two": {
      "owner_name": "Bo's Biches",
      "players_received": [
        {
          "Nick Castellanos": 3
        }
      ]
    }
  },
  {
    "date": 1659986095629,
    "owner_one": {
      "owner_name": "The Cavemen",
      "players_received": [
        {
          "Starling Marte": 12
        }
      ]
    },
    "owner_two": {
      "owner_name": "LeMahoe Round 2",
      "players_received": [
        {
          "Cole Irvin": 23
        }
      ]
    }
  },
  {
    "date": 1659974581709,
    "owner_one": {
      "owner_name": "The Cavemen",
      "players_received": [
        {
          "Fernando Tatis Jr.": 0
        }
      ]
    },
    "owner_two": {
      "owner_name": "I Did  Half a Xan",
      "players_received": [
        {
          "Chris Bassitt": 43
        }
      ]
    }
  },
  {
    "date": 1659968107601,
    "owner_one": {
      "owner_name": "A Team of White Sox",
      "players_received": [
        {
          "Dane Dunning": 7
        }
      ]
    },
    "owner_two": {
      "owner_name": "I Did  Half a Xan",
      "players_received": [
        {
          "Dylan Cease": 17
        }
      ]
    }
  },
  {
    "date": 1659887549724,
    "owner_one": {
      "owner_name": "LeMahoe Round 2",
      "players_received": [
        {
          "Ke'Bryan Hayes": 10
        }
      ]
    },
    "owner_two": {
      "owner_name": "The Cavemen",
      "players_received": [
        {
          "Jon Berti": -1
        }
      ]
    }
  },
  {
    "date": 1659883307892,
    "owner_one": {
      "owner_name": "Trea's Gaze",
      "players_received": [
        {
          "Braxton Garrett": 15
        }
      ]
    },
    "owner_two": {
      "owner_name": "LeMahoe Round 2",
      "players_received": [
        {
          "Kutter Crawford": 19
        }
      ]
    }
  },
  {
    "date": 1659837671819,
    "owner_one": {
      "owner_name": "The Cavemen",
      "players_received": [
        {
          "Ke'Bryan Hayes": 10
        },
        {
          "Alexis Diaz": 30
        },
        {
          "Martin Perez": 13
        },
        {
          "Framber Valdez": 27
        },
        {
          "Alec Bohm": 14
        }
      ]
    },
    "owner_two": {
      "owner_name": "A Team of White Sox",
      "players_received": [
        {
          "Jean Segura": 15
        },
        {
          "Logan Webb": 49
        },
        {
          "Garrett Cooper": 5
        },
        {
          "A.J. Puk": 9
        },
        {
          "Patrick Sandoval": 5
        },
        {
          "Byron Buxton": 16
        }
      ]
    }
  },
  {
    "date": 1659754044305,
    "owner_one": {
      "owner_name": "Thanks Ohtani",
      "players_received": [
        {
          "Marco Gonzales": 16
        }
      ]
    },
    "owner_two": {
      "owner_name": "LeMahoe Round 2",
      "players_received": [
        {
          "Wil Crowe": 2
        }
      ]
    }
  },
  {
    "date": 1659629482865,
    "owner_one": {
      "owner_name": "Trea's Gaze",
      "players_received": [
        {
          "Steven Kwan": 30
        }
      ]
    },
    "owner_two": {
      "owner_name": "Handy Diaz Nuts",
      "players_received": [
        {
          "Yandy Diaz": 16
        }
      ]
    }
  },
  {
    "date": 1659039919638,
    "owner_one": {
      "owner_name": "A Team of White Sox",
      "players_received": [
        {
          "Chris Archer": 33
        },
        {
          "Garrett Whitlock": 44
        },
        {
          "Framber Valdez": 58
        }
      ]
    },
    "owner_two": {
      "owner_name": "All about The Mets",
      "players_received": [
        {
          "Nick Castellanos": 40
        },
        {
          "Craig Kimbrel": 25
        },
        {
          "Triston McKenzie": 66
        }
      ]
    }
  },
  {
    "date": 1658410981908,
    "owner_one": {
      "owner_name": "Trea's Gaze",
      "players_received": [
        {
          "Esteury Ruiz": 0
        }
      ]
    },
    "owner_two": {
      "owner_name": "A Team of White Sox",
      "players_received": [
        {
          "Chris Sale": 0
        }
      ]
    }
  },
  {
    "date": 1658410900492,
    "owner_one": {
      "owner_name": "A Team of White Sox",
      "players_received": [
        {
          "Ryan Mountcastle": 23
        }
      ]
    },
    "owner_two": {
      "owner_name": "Trea's Gaze",
      "players_received": [
        {
          "Kyle Lewis": -1
        },
        {
          "Chris Sale": 0
        }
      ]
    }
  },
  {
    "date": 1658155257065,
    "owner_one": {
      "owner_name": "Trea's Geas",
      "players_received": [
        {
          "Hunter Renfroe": 64
        }
      ]
    },
    "owner_two": {
      "owner_name": "Trea's Gaze",
      "players_received": [
        {
          "Zach Plesac": 30
        }
      ]
    }
  },
  {
    "date": 1657876684274,
    "owner_one": {
      "owner_name": "Trea's Gaze",
      "players_received": [
        {
          "Freddy Peralta": 29
        },
        {
          "Taylor Rogers": 33
        }
      ]
    },
    "owner_two": {
      "owner_name": "EATING Astros",
      "players_received": [
        {
          "Marcus Stroman": 84
        },
        {
          "Ian Anderson": 52
        },
        {
          "Christopher Morel": 34
        }
      ]
    }
  },
  {
    "date": 1657392681866,
    "owner_one": {
      "owner_name": "EATING Astros",
      "players_received": [
        {
          "Tyler Wells": 21
        }
      ]
    },
    "owner_two": {
      "owner_name": "LeMahoe Round 2",
      "players_received": [
        {
          "Alex Verdugo": 68
        }
      ]
    }
  },
  {
    "date": 1656730713914,
    "owner_one": {
      "owner_name": "Players to be Named Later",
      "players_received": [
        {
          "Riley Greene": 50
        }
      ]
    },
    "owner_two": {
      "owner_name": "Trea's Gaze",
      "players_received": [
        {
          "Adley Rutschman": 98
        }
      ]
    }
  },
  {
    "date": 1656702384677,
    "owner_one": {
      "owner_name": "LeMahoe Round 2",
      "players_received": [
        {
          "Luis Urias": 70
        }
      ]
    },
    "owner_two": {
      "owner_name": "Handy Diaz Nuts",
      "players_received": [
        {
          "Jack Suwinski": 10
        }
      ]
    }
  },
  {
    "date": 1656624128783,
    "owner_one": {
      "owner_name": "Thanks Ohtani",
      "players_received": [
        {
          "Rafael Montero": 63
        },
        {
          "Aroldis Chapman": 46
        }
      ]
    },
    "owner_two": {
      "owner_name": "The Cavemen",
      "players_received": [
        {
          "Jon Gray": 84
        }
      ]
    }
  },
  {
    "date": 1655769857672,
    "owner_one": {
      "owner_name": "A Team of White Sox",
      "players_received": [
        {
          "Anthony DeSclafani": -1
        }
      ]
    },
    "owner_two": {
      "owner_name": "LeMahoe Round 2",
      "players_received": [
        {
          "AJ Pollock": 68
        }
      ]
    }
  },
  {
    "date": 1655410376739,
    "owner_one": {
      "owner_name": "Handy Diaz Nuts",
      "players_received": [
        {
          "Aaron Ashby": 78
        },
        {
          "Jurickson Profar": 103
        }
      ]
    },
    "owner_two": {
      "owner_name": "Trea's Gaze",
      "players_received": [
        {
          "Hunter Renfroe": 93
        },
        {
          "Tylor Megill": 7
        }
      ]
    }
  },
  {
    "date": 1655320844897,
    "owner_one": {
      "owner_name": "LeMahoe Round 2",
      "players_received": [
        {
          "Tyler Mahle": 104
        }
      ]
    },
    "owner_two": {
      "owner_name": "I Did  Half a Xan",
      "players_received": [
        {
          "Xander Bogaerts": 103
        }
      ]
    }
  },
  {
    "date": 1654832258189,
    "owner_one": {
      "owner_name": "LeMahoe Round 2",
      "players_received": [
        {
          "Jack Suwinski": 40
        },
        {
          "Alex Faedo": -6
        }
      ]
    },
    "owner_two": {
      "owner_name": "Thanks Ohtani",
      "players_received": [
        {
          "Jeffrey Springs": 102
        },
        {
          "Brandon Crawford": 29
        }
      ]
    }
  },
  {
    "date": 1654776315055,
    "owner_one": {
      "owner_name": "LeMahoe Round 2",
      "players_received": [
        {
          "DJ LeMahieu": 167
        }
      ]
    },
    "owner_two": {
      "owner_name": "All about The Mets",
      "players_received": [
        {
          "A.J. Minter": 107
        },
        {
          "Anthony Santander": 140
        }
      ]
    }
  },
  {
    "date": 1654776302747,
    "owner_one": {
      "owner_name": "Thanks Ohtani",
      "players_received": [
        {
          "Max Muncy": 113
        },
        {
          "Corey Knebel": 59
        }
      ]
    },
    "owner_two": {
      "owner_name": "All about The Mets",
      "players_received": [
        {
          "Wilmer Flores": 130
        }
      ]
    }
  },
  {
    "date": 1654711476018,
    "owner_one": {
      "owner_name": "A Team of White Sox",
      "players_received": [
        {
          "Devin Smeltzer": 56
        }
      ]
    },
    "owner_two": {
      "owner_name": "LeMahoe Round 2",
      "players_received": [
        {
          "Tanner Houck": 89
        }
      ]
    }
  },
  {
    "date": 1654636238729,
    "owner_one": {
      "owner_name": "A Team of White Sox",
      "players_received": [
        {
          "Sean Murphy": 135
        },
        {
          "Daniel Bard": 115
        }
      ]
    },
    "owner_two": {
      "owner_name": "LeMahoe Round 2",
      "players_received": [
        {
          "Jorge Lopez": 137
        }
      ]
    }
  },
  {
    "date": 1654625913894,
    "owner_one": {
      "owner_name": "All about The Mets",
      "players_received": [
        {
          "Enrique Hernandez": 0
        }
      ]
    },
    "owner_two": {
      "owner_name": "EATING Astros",
      "players_received": [
        {
          "Ranger Suarez": 147
        }
      ]
    }
  },
  {
    "date": 1654547879540,
    "owner_one": {
      "owner_name": "Trea's Gaze",
      "players_received": [
        {
          "Jake Cronenworth": 166
        }
      ]
    },
    "owner_two": {
      "owner_name": "The Cavemen",
      "players_received": [
        {
          "Chris Bassitt": 184
        }
      ]
    }
  },
  {
    "date": 1654225922947,
    "owner_one": {
      "owner_name": "Thanks Ohtani",
      "players_received": [
        {
          "Connor Joe": 82
        }
      ]
    },
    "owner_two": {
      "owner_name": "LeMahoe Round 2",
      "players_received": [
        {
          "Alejandro Kirk": 154
        }
      ]
    }
  },
  {
    "date": 1654224464125,
    "owner_one": {
      "owner_name": "A Team of White Sox",
      "players_received": [
        {
          "Ryan McMahon": 113
        },
        {
          "Dylan Bundy": 114
        }
      ]
    },
    "owner_two": {
      "owner_name": "Thanks Ohtani",
      "players_received": [
        {
          "Jean Segura": 13
        },
        {
          "German Marquez": 156
        }
      ]
    }
  },
  {
    "date": 1654093310073,
    "owner_one": {
      "owner_name": "A Team of White Sox",
      "players_received": [
        {
          "Martin Perez": 184
        },
        {
          "Bryan Reynolds": 140
        }
      ]
    },
    "owner_two": {
      "owner_name": "Trea's Gaze",
      "players_received": [
        {
          "Julio Urias": 249
        },
        {
          "Ryan Mountcastle": 130
        },
        {
          "Brandon Belt": 54
        }
      ]
    }
  },
  {
    "date": 1653760064879,
    "owner_one": {
      "owner_name": "A Team of White Sox",
      "players_received": [
        {
          "Willy Adames": 130
        },
        {
          "Johnny Cueto": 199
        }
      ]
    },
    "owner_two": {
      "owner_name": "The Cavemen",
      "players_received": [
        {
          "Emilio Pagan": 74
        },
        {
          "Jared Walsh": 44
        }
      ]
    }
  },
  {
    "date": 1653760025719,
    "owner_one": {
      "owner_name": "LeMahoe Round 2",
      "players_received": [
        {
          "Xander Bogaerts": 145
        },
        {
          "Max Fried": 226
        }
      ]
    },
    "owner_two": {
      "owner_name": "A Team of White Sox",
      "players_received": [
        {
          "Alec Bohm": 132
        },
        {
          "Brandon Drury": 188
        },
        {
          "Julio Urias": 259
        },
        {
          "Nick Castellanos": 105
        }
      ]
    }
  },
  {
    "date": 1653672850979,
    "owner_one": {
      "owner_name": "I Did  Half a Xan",
      "players_received": [
        {
          "Anthony Bass": 113
        },
        {
          "Adrian Houser": 30
        },
        {
          "Vladimir Guerrero Jr.": 215
        }
      ]
    },
    "owner_two": {
      "owner_name": "The Cavemen",
      "players_received": [
        {
          "Matt Olson": 194
        },
        {
          "Jazz Chisholm Jr.": 64
        }
      ]
    }
  },
  {
    "date": 1653340526156,
    "owner_one": {
      "owner_name": "Trea's Gaze",
      "players_received": [
        {
          "Austin Riley": 247
        }
      ]
    },
    "owner_two": {
      "owner_name": "Trea's Geas",
      "players_received": [
        {
          "Trevor Story": 85
        },
        {
          "Eugenio Suarez": 124
        }
      ]
    }
  },
  {
    "date": 1653261338108,
    "owner_one": {
      "owner_name": "A Team of White Sox",
      "players_received": [
        {
          "AJ Pollock": 116
        }
      ]
    },
    "owner_two": {
      "owner_name": "LeMahoe Round 2",
      "players_received": [
        {
          "John Schreiber": 150
        }
      ]
    }
  },
  {
    "date": 1653261251810,
    "owner_one": {
      "owner_name": "A Team of White Sox",
      "players_received": [
        {
          "Merrill Kelly": 232
        },
        {
          "Emilio Pagan": 94
        },
        {
          "Ben Gamel": 54
        }
      ]
    },
    "owner_two": {
      "owner_name": "LeMahoe Round 2",
      "players_received": [
        {
          "Anthony Santander": 171
        },
        {
          "AJ Pollock": 116
        },
        {
          "Carlos Santana": 133
        }
      ]
    }
  },
  {
    "date": 1653173269790,
    "owner_one": {
      "owner_name": "A Team of White Sox",
      "players_received": [
        {
          "AJ Pollock": 122
        }
      ]
    },
    "owner_two": {
      "owner_name": "LeMahoe Round 2",
      "players_received": [
        {
          "Wade Miley": 17
        }
      ]
    }
  },
  {
    "date": 1653173205830,
    "owner_one": {
      "owner_name": "A Team of White Sox",
      "players_received": [
        {
          "Brandon Belt": 54
        },
        {
          "Ryan Mountcastle": 147
        }
      ]
    },
    "owner_two": {
      "owner_name": "LeMahoe Round 2",
      "players_received": [
        {
          "Emilio Pagan": 94
        },
        {
          "AJ Pollock": 122
        },
        {
          "Tyler O'Neill": 71
        }
      ]
    }
  },
  {
    "date": 1652809910000,
    "owner_one": {
      "owner_name": "LeMahoe Round 2",
      "players_received": [
        {
          "Corbin Burnes": 304
        },
        {
          "Pete Alonso": 258
        }
      ]
    },
    "owner_two": {
      "owner_name": "Thanks Ohtani",
      "players_received": [
        {
          "Garrett Whitlock": 111
        },
        {
          "Wilmer Flores": 188
        },
        {
          "Shohei Ohtani": 432
        }
      ]
    }
  },
  {
    "date": 1651613496291,
    "owner_one": {
      "owner_name": "Trea's Gaze",
      "players_received": [
        {
          "Salvador Perez": 116
        },
        {
          "Mitch Haniger": 21
        },
        {
          "Eugenio Suarez": 162
        }
      ]
    },
    "owner_two": {
      "owner_name": "LeMahoe Round 2",
      "players_received": [
        {
          "Sean Murphy": 168
        },
        {
          "Alec Bohm": 158
        },
        {
          "Randy Arozarena": 211
        }
      ]
    }
  },
  {
    "date": 1651251506457,
    "owner_one": {
      "owner_name": "Trea's Gaze",
      "players_received": [
        {
          "Ian Anderson": 189
        },
        {
          "Alec Bohm": 163
        }
      ]
    },
    "owner_two": {
      "owner_name": "All about The Mets",
      "players_received": [
        {
          "Dany Jimenez": 77
        },
        {
          "Max Kepler": 141
        }
      ]
    }
  },
  {
    "date": 1651019468824,
    "owner_one": {
      "owner_name": "Players to be Named Later",
      "players_received": [
        {
          "Frank Schwindel": 72
        },
        {
          "Jonathan Schoop": 108
        }
      ]
    },
    "owner_two": {
      "owner_name": "A Team of White Sox",
      "players_received": [
        {
          "Anthony Santander": 233
        },
        {
          "Carlos Santana": 162
        }
      ]
    }
  },
  {
    "date": 1650917479017,
    "owner_one": {
      "owner_name": "A Team of White Sox",
      "players_received": [
        {
          "Elias Diaz": 93
        },
        {
          "Ke'Bryan Hayes": 150
        }
      ]
    },
    "owner_two": {
      "owner_name": "Thanks Ohtani",
      "players_received": [
        {
          "Gregory Soto": 159
        },
        {
          "Patrick Wisdom": 167
        }
      ]
    }
  },
  {
    "date": 1650903143637,
    "owner_one": {
      "owner_name": "A Team of White Sox",
      "players_received": [
        {
          "Patrick Wisdom": 167
        }
      ]
    },
    "owner_two": {
      "owner_name": "Bo's Biches",
      "players_received": [
        {
          "Javier Baez": 151
        }
      ]
    }
  },
  {
    "date": 1650903015844,
    "owner_one": {
      "owner_name": "LeMahoe Round 2",
      "players_received": [
        {
          "Daniel Bard": 190
        }
      ]
    },
    "owner_two": {
      "owner_name": "A Team of White Sox",
      "players_received": [
        {
          "Javier Baez": 151
        },
        {
          "Frank Schwindel": 72
        }
      ]
    }
  },
  {
    "date": 1650049321057,
    "owner_one": {
      "owner_name": "LeMahoe Round 2",
      "players_received": [
        {
          "John Means": 0
        }
      ]
    },
    "owner_two": {
      "owner_name": "A Team of White Sox",
      "players_received": [
        {
          "Tyler O'Neill": 98
        }
      ]
    }
  },
  {
    "date": 1650039692419,
    "owner_one": {
      "owner_name": "All about The Mets",
      "players_received": [
        {
          "Eric Lauer": 282
        },
        {
          "Miles Mikolas": 345
        }
      ]
    },
    "owner_two": {
      "owner_name": "LeMahoe Round 2",
      "players_received": [
        {
          "Garrett Whitlock": 182
        }
      ]
    }
  },
  {
    "date": 1650037521930,
    "owner_one": {
      "owner_name": "The Cavemen",
      "players_received": [
        {
          "Jesus Luzardo": 99
        }
      ]
    },
    "owner_two": {
      "owner_name": "Thanks Ohtani",
      "players_received": [
        {
          "Randal Grichuk": 177
        },
        {
          "Bailey Ober": 57
        }
      ]
    }
  },
  {
    "date": 1649948307692,
    "owner_one": {
      "owner_name": "Trea's Gaze",
      "players_received": [
        {
          "Max Kepler": 174
        },
        {
          "Sean Murphy": 196
        }
      ]
    },
    "owner_two": {
      "owner_name": "A Team of White Sox",
      "players_received": [
        {
          "John Means": 0
        }
      ]
    }
  },
  {
    "date": 1649034656795,
    "owner_one": {
      "owner_name": "A Team of White Sox",
      "players_received": [
        {
          "Gregory Soto": 190
        }
      ]
    },
    "owner_two": {
      "owner_name": "Handy Diaz Nuts",
      "players_received": [
        {
          "Juan Soto": 352
        }
      ]
    }
  },
  {
    "date": 1649034370785,
    "owner_one": {
      "owner_name": "The Cavemen",
      "players_received": [
        {
          "Kenley Jansen": 280
        }
      ]
    },
    "owner_two": {
      "owner_name": "All about The Mets",
      "players_received": [
        {
          "Corey Knebel": 155
        },
        {
          "Ian Anderson": 213
        }
      ]
    }
  },
  {
    "date": 1649034357971,
    "owner_one": {
      "owner_name": "Handy Diaz Nuts",
      "players_received": [
        {
          "Kolten Wong": 195
        },
        {
          "Carlos Carrasco": 308
        },
        {
          "Gregory Soto": 190
        }
      ]
    },
    "owner_two": {
      "owner_name": "A Team of White Sox",
      "players_received": [
        {
          "Juan Soto": 352
        },
        {
          "Zach Plesac": 204
        },
        {
          "Joey Gallo": 83
        }
      ]
    }
  },
  {
    "date": 1649033898308,
    "owner_one": {
      "owner_name": "Handy Diaz Nuts",
      "players_received": [
        {
          "Joey Gallo": 83
        }
      ]
    },
    "owner_two": {
      "owner_name": "A Team of White Sox",
      "players_received": [
        {
          "Kolten Wong": 195
        }
      ]
    }
  },
  {
    "date": 1649033893395,
    "owner_one": {
      "owner_name": "Handy Diaz Nuts",
      "players_received": [
        {
          "Zach Plesac": 204
        }
      ]
    },
    "owner_two": {
      "owner_name": "A Team of White Sox",
      "players_received": [
        {
          "Carlos Carrasco": 308
        }
      ]
    }
  },
  {
    "date": 1649033806904,
    "owner_one": {
      "owner_name": "Handy Diaz Nuts",
      "players_received": [
        {
          "Carlos Carrasco": 308
        },
        {
          "Kolten Wong": 195
        }
      ]
    },
    "owner_two": {
      "owner_name": "A Team of White Sox",
      "players_received": [
        {
          "Joey Gallo": 83
        },
        {
          "Zach Plesac": 204
        }
      ]
    }
  },
  {
    "date": 1649033671502,
    "owner_one": {
      "owner_name": "Handy Diaz Nuts",
      "players_received": [
        {
          "Zach Plesac": 204
        },
        {
          "Joey Gallo": 83
        }
      ]
    },
    "owner_two": {
      "owner_name": "A Team of White Sox",
      "players_received": [
        {
          "Carlos Carrasco": 308
        },
        {
          "Kolten Wong": 195
        }
      ]
    }
  },
  {
    "date": 1649033453005,
    "owner_one": {
      "owner_name": "All about The Mets",
      "players_received": [
        {
          "Yu Darvish": 379
        }
      ]
    },
    "owner_two": {
      "owner_name": "Handy Diaz Nuts",
      "players_received": [
        {
          "Joe Musgrove": 359
        }
      ]
    }
  },
  {
    "date": 1649033433902,
    "owner_one": {
      "owner_name": "A Team of White Sox",
      "players_received": [
        {
          "Joey Gallo": 83
        },
        {
          "Zach Plesac": 204
        }
      ]
    },
    "owner_two": {
      "owner_name": "Handy Diaz Nuts",
      "players_received": [
        {
          "Kolten Wong": 195
        },
        {
          "Carlos Carrasco": 308
        }
      ]
    }
  },
  {
    "date": 1649005731252,
    "owner_one": {
      "owner_name": "A Team of White Sox",
      "players_received": [
        {
          "Max Kepler": 186
        }
      ]
    },
    "owner_two": {
      "owner_name": "All about The Mets",
      "players_received": [
        {
          "Amed Rosario": 262
        }
      ]
    }
  },
  {
    "date": 1648834920354,
    "owner_one": {
      "owner_name": "LeMahoe Round 2",
      "players_received": [
        {
          "Dylan Floro": 89
        },
        {
          "Julio Urias": 368
        },
        {
          "Nick Castellanos": 192
        }
      ]
    },
    "owner_two": {
      "owner_name": "A Team of White Sox",
      "players_received": [
        {
          "Xander Bogaerts": 256
        },
        {
          "Gregory Soto": 190
        },
        {
          "Max Fried": 371
        },
        {
          "AJ Pollock": 156
        }
      ]
    }
  },
  {
    "date": 1648745349237,
    "owner_one": {
      "owner_name": "LeMahoe Round 2",
      "players_received": [
        {
          "Rafael Devers": 317
        },
        {
          "Anthony DeSclafani": 16
        },
        {
          "Javier Baez": 161
        },
        {
          "Shohei Ohtani": 625
        }
      ]
    },
    "owner_two": {
      "owner_name": "I Did  Half a Xan",
      "players_received": [
        {
          "Max Scherzer": 335
        },
        {
          "Jesse Winker": 195
        },
        {
          "Ozzie Albies": 139
        },
        {
          "Matt Olson": 291
        },
        {
          "Tyler Mahle": 275
        }
      ]
    }
  },
  {
    "date": 1648678783567,
    "owner_one": {
      "owner_name": "A Team of White Sox",
      "players_received": [
        {
          "Nick Castellanos": 192
        },
        {
          "Julio Urias": 368
        },
        {
          "Jose Abreu": 294
        }
      ]
    },
    "owner_two": {
      "owner_name": "The Cavemen",
      "players_received": [
        {
          "Jose Ramirez": 404
        },
        {
          "Andrew Benintendi": 233
        },
        {
          "Ian Anderson": 213
        }
      ]
    }
  },
  {
    "date": 1648678747697,
    "owner_one": {
      "owner_name": "A Team of White Sox",
      "players_received": [
        {
          "Kolten Wong": 195
        },
        {
          "Eloy Jimenez": 76
        }
      ]
    },
    "owner_two": {
      "owner_name": "I Did  Half a Xan",
      "players_received": [
        {
          "Fernando Tatis Jr.": 0
        }
      ]
    }
  },
  {
    "date": 1648650088072,
    "owner_one": {
      "owner_name": "The Cavemen",
      "players_received": [
        {
          "Giancarlo Stanton": 193
        },
        {
          "Jose Abreu": 294
        },
        {
          "Josh Rojas": 192
        },
        {
          "Avisail Garcia": 89
        }
      ]
    },
    "owner_two": {
      "owner_name": "A Team of White Sox",
      "players_received": [
        {
          "Adam Haseley": 6
        },
        {
          "Elieser Hernandez": 97
        },
        {
          "Josh Harrison": 143
        },
        {
          "Jose Ramirez": 404
        }
      ]
    }
  },
  {
    "date": 1648648973767,
    "owner_one": {
      "owner_name": "The Cavemen",
      "players_received": [
        {
          "Elieser Hernandez": 97
        },
        {
          "Jose Ramirez": 404
        },
        {
          "Adam Haseley": 6
        },
        {
          "Josh Harrison": 143
        }
      ]
    },
    "owner_two": {
      "owner_name": "A Team of White Sox",
      "players_received": [
        {
          "Jose Abreu": 294
        },
        {
          "Avisail Garcia": 89
        },
        {
          "Giancarlo Stanton": 193
        },
        {
          "Josh Rojas": 192
        }
      ]
    }
  },
  {
    "date": 1648604536413,
    "owner_one": {
      "owner_name": "A Team of White Sox",
      "players_received": [
        {
          "Yoan Moncada": 85
        }
      ]
    },
    "owner_two": {
      "owner_name": "LeMahoe Round 2",
      "players_received": [
        {
          "Wilmer Flores": 264
        },
        {
          "Ryan Mountcastle": 196
        }
      ]
    }
  }
]